{
    "/js/app.js": "/js/app.js",
    "/css/app.css": "/css/app.css",
    "/0.502ff927a497d004dd69.hot-update.js": "/0.502ff927a497d004dd69.hot-update.js",
    "/0.003745d32bdf682bf947.hot-update.js": "/0.003745d32bdf682bf947.hot-update.js",
    "/0.9e82e03eba8bc10f219e.hot-update.js": "/0.9e82e03eba8bc10f219e.hot-update.js",
    "/0.1b24240355eb37b2efbd.hot-update.js": "/0.1b24240355eb37b2efbd.hot-update.js",
    "/0.a6a5c5876475a1719cb8.hot-update.js": "/0.a6a5c5876475a1719cb8.hot-update.js",
    "/0.cdff92a24c9ad5906341.hot-update.js": "/0.cdff92a24c9ad5906341.hot-update.js",
    "/0.6b1260c56b5a3aa1831a.hot-update.js": "/0.6b1260c56b5a3aa1831a.hot-update.js",
    "/0.1c7b6d54a9ce818047a0.hot-update.js": "/0.1c7b6d54a9ce818047a0.hot-update.js",
    "/0.77a5f031dd7eb75416d2.hot-update.js": "/0.77a5f031dd7eb75416d2.hot-update.js",
    "/0.777be768419db5023d1c.hot-update.js": "/0.777be768419db5023d1c.hot-update.js",
    "/0.e00d263eb4eb636209ef.hot-update.js": "/0.e00d263eb4eb636209ef.hot-update.js",
    "/0.aff59770ee7d9ba76023.hot-update.js": "/0.aff59770ee7d9ba76023.hot-update.js",
    "/0.9f4516649ab3289501a8.hot-update.js": "/0.9f4516649ab3289501a8.hot-update.js",
    "/0.de92521140f67bdfadf4.hot-update.js": "/0.de92521140f67bdfadf4.hot-update.js",
    "/0.63d4aad73bd7f5fd1149.hot-update.js": "/0.63d4aad73bd7f5fd1149.hot-update.js",
    "/0.5911648256146378621b.hot-update.js": "/0.5911648256146378621b.hot-update.js",
    "/0.ae521ef9d4d7631a6411.hot-update.js": "/0.ae521ef9d4d7631a6411.hot-update.js",
    "/0.e96ca03d64539f42a507.hot-update.js": "/0.e96ca03d64539f42a507.hot-update.js",
    "/0.ee99b55f8d3e909e221a.hot-update.js": "/0.ee99b55f8d3e909e221a.hot-update.js",
    "/0.05e4816e0857f55b761e.hot-update.js": "/0.05e4816e0857f55b761e.hot-update.js",
    "/0.fe2934442986941efd38.hot-update.js": "/0.fe2934442986941efd38.hot-update.js",
    "/0.c7b0a83588ccb65efca0.hot-update.js": "/0.c7b0a83588ccb65efca0.hot-update.js",
    "/0.668b1320e281afa13ecd.hot-update.js": "/0.668b1320e281afa13ecd.hot-update.js",
    "/0.6ed5c55b3002ca258d50.hot-update.js": "/0.6ed5c55b3002ca258d50.hot-update.js",
    "/0.930b5f22245f685537ab.hot-update.js": "/0.930b5f22245f685537ab.hot-update.js",
    "/0.06b29957fb0e665ead19.hot-update.js": "/0.06b29957fb0e665ead19.hot-update.js",
    "/0.f8caa4df2015cce04b17.hot-update.js": "/0.f8caa4df2015cce04b17.hot-update.js",
    "/0.fb5fd04f5b7504f60290.hot-update.js": "/0.fb5fd04f5b7504f60290.hot-update.js",
    "/0.9cccf1d38e6e48d63447.hot-update.js": "/0.9cccf1d38e6e48d63447.hot-update.js",
    "/0.499f942752924cb0e041.hot-update.js": "/0.499f942752924cb0e041.hot-update.js",
    "/0.0907470929efc4b0b579.hot-update.js": "/0.0907470929efc4b0b579.hot-update.js",
    "/0.0c054d49e3807c59a20c.hot-update.js": "/0.0c054d49e3807c59a20c.hot-update.js",
    "/0.7d898b1ceb5ca8b07ce1.hot-update.js": "/0.7d898b1ceb5ca8b07ce1.hot-update.js",
    "/0.9ff150a225232986cb5e.hot-update.js": "/0.9ff150a225232986cb5e.hot-update.js",
    "/0.cb074e7d480397bbf75b.hot-update.js": "/0.cb074e7d480397bbf75b.hot-update.js",
    "/0.7e1ad4e773f5935bc603.hot-update.js": "/0.7e1ad4e773f5935bc603.hot-update.js",
    "/0.961cf4998bf23d359b7f.hot-update.js": "/0.961cf4998bf23d359b7f.hot-update.js",
    "/0.8af9a9ab0f53b116e52a.hot-update.js": "/0.8af9a9ab0f53b116e52a.hot-update.js",
    "/0.f6a61aab502192ffe5fd.hot-update.js": "/0.f6a61aab502192ffe5fd.hot-update.js",
    "/0.88777324aa2132e92097.hot-update.js": "/0.88777324aa2132e92097.hot-update.js",
    "/0.faf9577d9bf85c5fa247.hot-update.js": "/0.faf9577d9bf85c5fa247.hot-update.js",
    "/0.d078eb7ae9cec5ff694d.hot-update.js": "/0.d078eb7ae9cec5ff694d.hot-update.js",
    "/0.2d17e177640dbb6896de.hot-update.js": "/0.2d17e177640dbb6896de.hot-update.js",
    "/0.b05a3b263684311c04d1.hot-update.js": "/0.b05a3b263684311c04d1.hot-update.js",
    "/0.80fb927c1dbfe6a53b79.hot-update.js": "/0.80fb927c1dbfe6a53b79.hot-update.js",
    "/0.9e924f2835de80f689fc.hot-update.js": "/0.9e924f2835de80f689fc.hot-update.js",
    "/0.e90f793bd7802b40cb29.hot-update.js": "/0.e90f793bd7802b40cb29.hot-update.js",
    "/0.8fe00e674f4d83e2a1a8.hot-update.js": "/0.8fe00e674f4d83e2a1a8.hot-update.js",
    "/0.87df95d1cced542189d9.hot-update.js": "/0.87df95d1cced542189d9.hot-update.js",
    "/0.a3ffd9d749f3ec928bf3.hot-update.js": "/0.a3ffd9d749f3ec928bf3.hot-update.js",
    "/0.73b33cd6a93ec9334414.hot-update.js": "/0.73b33cd6a93ec9334414.hot-update.js",
    "/0.e79601e986bcff797431.hot-update.js": "/0.e79601e986bcff797431.hot-update.js",
    "/0.b5b3ee10d116572511dc.hot-update.js": "/0.b5b3ee10d116572511dc.hot-update.js",
    "/0.e5a5b31a2b766c7fbc32.hot-update.js": "/0.e5a5b31a2b766c7fbc32.hot-update.js",
    "/0.72855ac65e7bee720ff4.hot-update.js": "/0.72855ac65e7bee720ff4.hot-update.js",
    "/0.568df0b83d64fe37007e.hot-update.js": "/0.568df0b83d64fe37007e.hot-update.js",
    "/0.bb4a234ee9b659008653.hot-update.js": "/0.bb4a234ee9b659008653.hot-update.js"
}