{
    "/js/app.js": "/js/app.js",
    "/css/app.css": "/css/app.css",
    "/0.db3da5dbfa895cbeaf8b.hot-update.js": "/0.db3da5dbfa895cbeaf8b.hot-update.js",
    "/0.80bb297f7779f0a7c951.hot-update.js": "/0.80bb297f7779f0a7c951.hot-update.js",
    "/0.e905dacda5003983cd10.hot-update.js": "/0.e905dacda5003983cd10.hot-update.js",
    "/0.61da272a86a9d1e19b75.hot-update.js": "/0.61da272a86a9d1e19b75.hot-update.js",
    "/0.79c2a4755ecf823ecfeb.hot-update.js": "/0.79c2a4755ecf823ecfeb.hot-update.js",
    "/0.74c8673d1bfe2320ff76.hot-update.js": "/0.74c8673d1bfe2320ff76.hot-update.js",
    "/0.f4ce36f8bb69ecf08d76.hot-update.js": "/0.f4ce36f8bb69ecf08d76.hot-update.js",
    "/0.d4574abec6dde447d402.hot-update.js": "/0.d4574abec6dde447d402.hot-update.js",
    "/0.8c9b89eb0f7123f3f771.hot-update.js": "/0.8c9b89eb0f7123f3f771.hot-update.js",
    "/0.0f87292fd82b119e16ef.hot-update.js": "/0.0f87292fd82b119e16ef.hot-update.js",
    "/0.4412506376729dcedc47.hot-update.js": "/0.4412506376729dcedc47.hot-update.js",
    "/0.b703be136e81e922d824.hot-update.js": "/0.b703be136e81e922d824.hot-update.js",
    "/0.0c765eec50c054e579b7.hot-update.js": "/0.0c765eec50c054e579b7.hot-update.js",
    "/0.8be2451a6db792dce9f8.hot-update.js": "/0.8be2451a6db792dce9f8.hot-update.js",
    "/0.f79914ad04346dff9b65.hot-update.js": "/0.f79914ad04346dff9b65.hot-update.js",
    "/0.d327ec9de4027f0c0d1e.hot-update.js": "/0.d327ec9de4027f0c0d1e.hot-update.js",
    "/0.a61e1c24d618457393ce.hot-update.js": "/0.a61e1c24d618457393ce.hot-update.js",
    "/0.f2647a257bc430c36baa.hot-update.js": "/0.f2647a257bc430c36baa.hot-update.js",
    "/0.cdb6b6a9a1474d41acf1.hot-update.js": "/0.cdb6b6a9a1474d41acf1.hot-update.js",
    "/0.b372adecad757539038c.hot-update.js": "/0.b372adecad757539038c.hot-update.js",
    "/0.9d407aefc45558c28d89.hot-update.js": "/0.9d407aefc45558c28d89.hot-update.js",
    "/0.bec6a66d6cb15138519a.hot-update.js": "/0.bec6a66d6cb15138519a.hot-update.js",
    "/0.ee67efa0e1d6c8863133.hot-update.js": "/0.ee67efa0e1d6c8863133.hot-update.js",
    "/0.48db4123390feed9c054.hot-update.js": "/0.48db4123390feed9c054.hot-update.js",
    "/0.1b815dd8930e8a24d0e7.hot-update.js": "/0.1b815dd8930e8a24d0e7.hot-update.js",
    "/0.21493914613c468cb625.hot-update.js": "/0.21493914613c468cb625.hot-update.js",
    "/0.eb621aa7bd8c5a09be83.hot-update.js": "/0.eb621aa7bd8c5a09be83.hot-update.js",
    "/0.d4eb732b1bcc4e6e219a.hot-update.js": "/0.d4eb732b1bcc4e6e219a.hot-update.js",
    "/0.0aed04e4c02c5ef931d1.hot-update.js": "/0.0aed04e4c02c5ef931d1.hot-update.js",
    "/0.c98e4cb8f7062d1eecfd.hot-update.js": "/0.c98e4cb8f7062d1eecfd.hot-update.js",
    "/0.2d16a0515eb9ed5a4d27.hot-update.js": "/0.2d16a0515eb9ed5a4d27.hot-update.js",
    "/0.ffddb6887c3d79a2a410.hot-update.js": "/0.ffddb6887c3d79a2a410.hot-update.js",
    "/0.c158bfe0367093d85f76.hot-update.js": "/0.c158bfe0367093d85f76.hot-update.js",
    "/0.4bb9d737a8dd8ccce902.hot-update.js": "/0.4bb9d737a8dd8ccce902.hot-update.js",
    "/0.ac3e328ca87459e3965c.hot-update.js": "/0.ac3e328ca87459e3965c.hot-update.js",
    "/0.b431561ee65da15acbd7.hot-update.js": "/0.b431561ee65da15acbd7.hot-update.js",
    "/0.c1b9ad4c1f0b445c52ee.hot-update.js": "/0.c1b9ad4c1f0b445c52ee.hot-update.js",
    "/0.83559e9ba290df9cbcfa.hot-update.js": "/0.83559e9ba290df9cbcfa.hot-update.js",
    "/0.b8555841efa99185780d.hot-update.js": "/0.b8555841efa99185780d.hot-update.js",
    "/0.bbbc06317c4a1a06adcb.hot-update.js": "/0.bbbc06317c4a1a06adcb.hot-update.js",
    "/0.a2784198beaff64fec15.hot-update.js": "/0.a2784198beaff64fec15.hot-update.js",
    "/0.2b961c29f32337f34784.hot-update.js": "/0.2b961c29f32337f34784.hot-update.js",
    "/0.d8ec9c78fa4446071c9c.hot-update.js": "/0.d8ec9c78fa4446071c9c.hot-update.js",
    "/0.f4a2c4e1814431568445.hot-update.js": "/0.f4a2c4e1814431568445.hot-update.js",
    "/0.f9425048ba70f7dbb9ba.hot-update.js": "/0.f9425048ba70f7dbb9ba.hot-update.js",
    "/0.fecc74340ade318473b2.hot-update.js": "/0.fecc74340ade318473b2.hot-update.js",
    "/0.cb01754ad3e418a4d6b1.hot-update.js": "/0.cb01754ad3e418a4d6b1.hot-update.js",
    "/0.9989e92eeaad6df68131.hot-update.js": "/0.9989e92eeaad6df68131.hot-update.js",
    "/0.b960da180da602b1ee13.hot-update.js": "/0.b960da180da602b1ee13.hot-update.js",
    "/0.cde37befbe851e721e8c.hot-update.js": "/0.cde37befbe851e721e8c.hot-update.js",
    "/0.4be73f74d8074637354d.hot-update.js": "/0.4be73f74d8074637354d.hot-update.js",
    "/0.4a491cfd856d06f74446.hot-update.js": "/0.4a491cfd856d06f74446.hot-update.js",
    "/0.a3efb9a95e65005077b2.hot-update.js": "/0.a3efb9a95e65005077b2.hot-update.js",
    "/0.fa775fdff82b20285fc3.hot-update.js": "/0.fa775fdff82b20285fc3.hot-update.js",
    "/0.ba2e6b53e7fed8915e59.hot-update.js": "/0.ba2e6b53e7fed8915e59.hot-update.js",
    "/0.fb0bd82360a12b9ae572.hot-update.js": "/0.fb0bd82360a12b9ae572.hot-update.js",
    "/0.ec3d573f56374a7d5f54.hot-update.js": "/0.ec3d573f56374a7d5f54.hot-update.js",
    "/0.d4a6400023fa8837546b.hot-update.js": "/0.d4a6400023fa8837546b.hot-update.js",
    "/0.082ae959d311fafc303b.hot-update.js": "/0.082ae959d311fafc303b.hot-update.js",
    "/0.689d84ddb3284a487aef.hot-update.js": "/0.689d84ddb3284a487aef.hot-update.js",
    "/0.f83472bdd04a519fb4ea.hot-update.js": "/0.f83472bdd04a519fb4ea.hot-update.js",
    "/0.e776a571f6be17596e94.hot-update.js": "/0.e776a571f6be17596e94.hot-update.js",
    "/0.f6910048d8b4cef8298c.hot-update.js": "/0.f6910048d8b4cef8298c.hot-update.js",
    "/0.38a62b25960d594f574b.hot-update.js": "/0.38a62b25960d594f574b.hot-update.js",
    "/0.d80ba4dbb4cf34683170.hot-update.js": "/0.d80ba4dbb4cf34683170.hot-update.js",
    "/0.63431ef97bac7177a63f.hot-update.js": "/0.63431ef97bac7177a63f.hot-update.js",
    "/0.bf04832294a62da858bc.hot-update.js": "/0.bf04832294a62da858bc.hot-update.js",
    "/0.a0b4411740c210092c43.hot-update.js": "/0.a0b4411740c210092c43.hot-update.js",
    "/0.01867ae770ef6af17a98.hot-update.js": "/0.01867ae770ef6af17a98.hot-update.js",
    "/0.86320982b9307f8982b3.hot-update.js": "/0.86320982b9307f8982b3.hot-update.js",
    "/0.6da0d5708385731091cd.hot-update.js": "/0.6da0d5708385731091cd.hot-update.js",
    "/0.164058173140b5a424b9.hot-update.js": "/0.164058173140b5a424b9.hot-update.js",
    "/0.8df2a0dcf6674fdbc89f.hot-update.js": "/0.8df2a0dcf6674fdbc89f.hot-update.js",
    "/0.d05dd0577de8d01713bb.hot-update.js": "/0.d05dd0577de8d01713bb.hot-update.js",
    "/0.560a02449ee8419e6cdf.hot-update.js": "/0.560a02449ee8419e6cdf.hot-update.js",
    "/0.59163504d74758fca3e3.hot-update.js": "/0.59163504d74758fca3e3.hot-update.js",
    "/0.a2fa51cfe7acff8182f8.hot-update.js": "/0.a2fa51cfe7acff8182f8.hot-update.js",
    "/0.1977947ea4a317207d63.hot-update.js": "/0.1977947ea4a317207d63.hot-update.js",
    "/0.4d2fffcf12e6fb5ebeb8.hot-update.js": "/0.4d2fffcf12e6fb5ebeb8.hot-update.js",
    "/0.f5c8653dae2167f56c63.hot-update.js": "/0.f5c8653dae2167f56c63.hot-update.js",
    "/0.4525f1ca4822ccb68911.hot-update.js": "/0.4525f1ca4822ccb68911.hot-update.js",
    "/0.0d6c892d8173f43681a4.hot-update.js": "/0.0d6c892d8173f43681a4.hot-update.js",
    "/0.912881cf111fb5e27789.hot-update.js": "/0.912881cf111fb5e27789.hot-update.js",
    "/0.2e66b5e791a669fc1674.hot-update.js": "/0.2e66b5e791a669fc1674.hot-update.js",
    "/0.40369674f11417060c4b.hot-update.js": "/0.40369674f11417060c4b.hot-update.js",
    "/0.c69042d7519fdb84e554.hot-update.js": "/0.c69042d7519fdb84e554.hot-update.js",
    "/0.f69f3133305ba009442e.hot-update.js": "/0.f69f3133305ba009442e.hot-update.js",
    "/0.c4c6f79e885d6bf18c9e.hot-update.js": "/0.c4c6f79e885d6bf18c9e.hot-update.js",
    "/0.c25c1f7b9d9cb3fa4e3a.hot-update.js": "/0.c25c1f7b9d9cb3fa4e3a.hot-update.js",
    "/0.39cd46cb79223ef7ce07.hot-update.js": "/0.39cd46cb79223ef7ce07.hot-update.js",
    "/0.e5c0fcc2f138d1d583cc.hot-update.js": "/0.e5c0fcc2f138d1d583cc.hot-update.js",
    "/0.4d6d311973e3b4a5534b.hot-update.js": "/0.4d6d311973e3b4a5534b.hot-update.js",
    "/0.ff25ccdb890a7f39f70a.hot-update.js": "/0.ff25ccdb890a7f39f70a.hot-update.js",
    "/0.f388e2eedceb86629253.hot-update.js": "/0.f388e2eedceb86629253.hot-update.js",
    "/0.722d3710175a573191bd.hot-update.js": "/0.722d3710175a573191bd.hot-update.js",
    "/0.41aa658a329c308d6602.hot-update.js": "/0.41aa658a329c308d6602.hot-update.js",
    "/0.0728eecab26cc9566f7b.hot-update.js": "/0.0728eecab26cc9566f7b.hot-update.js",
    "/0.444c7ed89b5335412e9d.hot-update.js": "/0.444c7ed89b5335412e9d.hot-update.js",
    "/0.dd5601e4a3d14b04f909.hot-update.js": "/0.dd5601e4a3d14b04f909.hot-update.js",
    "/0.bc2bcdba0585ec4530fa.hot-update.js": "/0.bc2bcdba0585ec4530fa.hot-update.js",
    "/0.05aa8f0f2f773189067a.hot-update.js": "/0.05aa8f0f2f773189067a.hot-update.js",
    "/0.0a7994bff362aca62a94.hot-update.js": "/0.0a7994bff362aca62a94.hot-update.js",
    "/0.03d43f566cc98cc8aa5a.hot-update.js": "/0.03d43f566cc98cc8aa5a.hot-update.js",
    "/0.e47f1ac24db3d38aa56e.hot-update.js": "/0.e47f1ac24db3d38aa56e.hot-update.js",
    "/0.d7a758452f7e02ec7bbc.hot-update.js": "/0.d7a758452f7e02ec7bbc.hot-update.js"
}